{
	"folders": {},
	"connections": {
		"oracle_thin-18962b140ad-7493d880c0bdc69b": {
			"provider": "oracle",
			"driver": "oracle_thin",
			"name": "ORCL",
			"save-password": true,
			"configuration": {
				"host": "localhost",
				"port": "1521",
				"database": "ORCL",
				"url": "jdbc:oracle:thin:@//localhost:1521/ORCL",
				"configurationType": "MANUAL",
				"home": "C:\\Users\\Shinix\\Downloads\\WINDOWS.X64_193000_db_home",
				"type": "dev",
				"provider-properties": {
					"@dbeaver-connection-type@": "BASIC",
					"@dbeaver-sid-service@": "SERVICE"
				},
				"auth-model": "oracle_native"
			}
		}
	},
	"connection-types": {
		"dev": {
			"name": "Development",
			"color": "255,255,255",
			"description": "Regular development database",
			"auto-commit": true,
			"confirm-execute": false,
			"confirm-data-change": false,
			"smart-commit": false,
			"smart-commit-recover": true,
			"auto-close-transactions": true,
			"close-transactions-period": 1800
		}
	}
}